virusai/__init__.py
virusai/virus.py
virusai-1.0.1.dist-info/METADATA
virusai-1.0.1.dist-info/WHEEL
virusai-1.0.1.dist-info/top_level.txt
virusai-1.0.1.dist-info/RECORD
